README.md
setup.cfg
setup.py
druidpy/__init__.py
druidpy/druid.py
druidpy.egg-info/PKG-INFO
druidpy.egg-info/SOURCES.txt
druidpy.egg-info/dependency_links.txt
druidpy.egg-info/top_level.txt