Metadata-Version: 2.1
Name: druidpy
Version: 1.0.4
Summary: A package which provides minimum required methods for working with Druid through Python!
Home-page: https://github.com/Naresh-kumar-B-N/druidpy/archive/v1.0.4.tar.gz
Author: Naresh Kumar B N
Author-email: nareshbn007@gmail.com
License: UNKNOWN
Platform: UNKNOWN
Classifier: Programming Language :: Python :: 3
Classifier: License :: OSI Approved :: MIT License
Classifier: Operating System :: OS Independent
